haze_library-1.1.3.dist-info/METADATA
haze_library-1.1.3.dist-info/WHEEL
haze_library-1.1.3.dist-info/licenses/LICENSE
haze_library/__init__.py
haze_library/__init__.pyi
haze_library/accessor.py
haze_library/ai_indicators.py
haze_library/api/__init__.py
haze_library/api/main.py
haze_library/api/models/__init__.py
haze_library/api/models/requests.py
haze_library/api/models/responses.py
haze_library/api/routes/__init__.py
haze_library/api/routes/execution.py
haze_library/api/routes/indicators.py
haze_library/api/routes/streaming.py
haze_library/exceptions.py
haze_library/execution/__init__.py
haze_library/execution/engine.py
haze_library/execution/errors.py
haze_library/execution/llm_tools.py
haze_library/execution/models.py
haze_library/execution/permissions.py
haze_library/execution/providers/__init__.py
haze_library/execution/providers/base.py
haze_library/execution/providers/ccxt_provider.py
haze_library/execution/providers/memory.py
haze_library/execution/risk.py
haze_library/haze_library.cpython-314-x86_64-linux-gnu.so
haze_library/haze_library.pyi
haze_library/lt_indicators.py
haze_library/numpy_compat.py
haze_library/polars_ta.py
haze_library/py.typed
haze_library/streaming.py
haze_library/torch_ta.py
haze_library-1.1.3.dist-info/RECORD
