Metadata-Version: 2.4
Name: haze-library
Version: 1.1.3
Classifier: Development Status :: 5 - Production/Stable
Classifier: Intended Audience :: Financial and Insurance Industry
Classifier: License :: Other/Proprietary License
Classifier: Programming Language :: Python :: 3
Classifier: Programming Language :: Python :: 3.14
Classifier: Programming Language :: Python :: 3 :: Only
Classifier: Programming Language :: Rust
Classifier: Topic :: Office/Business :: Financial :: Investment
Classifier: Topic :: Scientific/Engineering :: Information Analysis
Requires-Dist: numpy>=2.4.0
Requires-Dist: pandas>=2.3.3
Requires-Dist: ccxt==4.5.29 ; extra == 'execution'
Requires-Dist: fastapi>=0.115.0 ; extra == 'api'
Requires-Dist: uvicorn[standard]>=0.34.0 ; extra == 'api'
Requires-Dist: pydantic>=2.10.0 ; extra == 'api'
Requires-Dist: pytest==9.0.2 ; extra == 'dev'
Requires-Dist: pytest-cov==7.0.0 ; extra == 'dev'
Requires-Dist: black==25.12.0 ; extra == 'dev'
Requires-Dist: isort==7.0.0 ; extra == 'dev'
Requires-Dist: mypy==1.19.1 ; extra == 'dev'
Requires-Dist: sphinx==9.0.4 ; extra == 'dev'
Requires-Dist: sphinx-rtd-theme==3.0.2 ; extra == 'dev'
Requires-Dist: pytest==9.0.2 ; extra == 'test'
Requires-Dist: pytest-cov==7.0.0 ; extra == 'test'
Requires-Dist: pytest-benchmark==5.2.3 ; extra == 'test'
Requires-Dist: ta-lib==0.6.8 ; extra == 'test-talib'
Requires-Dist: sphinx==9.0.4 ; extra == 'docs'
Requires-Dist: sphinx-rtd-theme==3.0.2 ; extra == 'docs'
Provides-Extra: execution
Provides-Extra: api
Provides-Extra: dev
Provides-Extra: test
Provides-Extra: test-talib
Provides-Extra: docs
License-File: LICENSE
Summary: High-performance quantitative trading indicators library with Rust backend
Keywords: trading,indicators,quantitative,technical-analysis,rust
Home-Page: https://github.com/kwannz/haze
Author-email: Haze Team <team@haze-library.com>
Maintainer-email: Haze Team <team@haze-library.com>
Requires-Python: >=3.14
Project-URL: Homepage, https://github.com/kwannz/haze
Project-URL: Documentation, https://github.com/kwannz/haze
Project-URL: Repository, https://github.com/kwannz/haze
Project-URL: Issues, https://github.com/kwannz/haze/issues
Project-URL: Changelog, https://github.com/kwannz/haze/blob/main/CHANGELOG.md
